{
  "project_info": {
    "project_number": "737697295441",
    "firebase_url": "https://brorkout-dce32-default-rtdb.europe-west1.firebasedatabase.app",
    "project_id": "brorkout-dce32",
    "storage_bucket": "brorkout-dce32.appspot.com"
  },
  "client": [
    {
      "client_info": {
        "mobilesdk_app_id": "1:737697295441:android:8fcc1194baf64c04689c70",
        "android_client_info": {
          "package_name": "com.andrea.belotti.brorkout"
        }
      },
      "oauth_client": [],
      "api_key": [
        {
          "current_key": "AIzaSyAHKmrFnEN2OgkHsHzYRfHbDeUCbun2qKQ"
        }
      ],
      "services": {
        "appinvite_service": {
          "other_platform_oauth_client": []
        }
      }
    }
  ],
  "configuration_version": "1"
}